trinkets/__init__.py
trinkets/archive.py
trinkets/calculate.py
trinkets/notify.py
trinkets/visualize.py
trinkets-0.2.5.dist-info/LICENSE
trinkets-0.2.5.dist-info/METADATA
trinkets-0.2.5.dist-info/WHEEL
trinkets-0.2.5.dist-info/top_level.txt
trinkets-0.2.5.dist-info/RECORD
